{"description":"SQL constraint that is used to specify rules for data in a table,","fields":[],"relationships":[],"properties":{"constraint_type":{"type":"string","description":"Classification of the constraint, can be one of the following values: PRIMARY KEY, FOREIGN KEY, UNIQUE, CHECK","is_array":false,"validated":false,"displayInChild":false,"restricted":false,"label":{"default":"Constraint Type","en":"Constraint Type"}},"enforced":{"type":"bool","description":"Indicates whether the constraint is checked when inserting new rows to table or updating existing rows.","is_array":false,"validated":false,"displayInChild":false,"restricted":false,"label":{"default":"Is Enforced","en":"Is Enforced"}},"description":{"type":"string","description":"Text description of the constraint used as a comment","is_array":false,"validated":false,"displayInChild":false,"restricted":false},"notes":{"type":"string","description":"Free form textual notes that a user can add","is_array":false,"validated":false,"displayInChild":false,"restricted":false}},"localized_metadata_attributes":{"name":{"default":"Physical model constraint","en":"Physical model constraint","de":"Einschränkung für physisches Modell","es":"Restricción de modelo físico","fr":"Contrainte du modèle physique","it":"Vincolo del modello fisico","ja":"物理モデル制約","ko":"물리적 모델 제한조건","pt":"Restrição do modelo físico","ru":"Ограничение физической модели","sv":"Fysisk modellregel","zh":"物理模型约束","zh-TW":"實體模型限制"}},"identity":{"strategy":"DUPLICATE_DETECTION_BY_NAME_AND_RESOURCE_KEY"},"global_search_searchable":[],"attribute_only":false,"is_column_custom_attribute":false,"can_have_image":false,"version":1,"name":"ibm_physical_model_constraint","scope":"GLOBAL","allow_decorators":true}